<?xml version="1.0" encoding="utf-8" ?>
<dwsync>
<file name="1.jpg" server="vacationhosting.com//public_html/" local="131578833600000000" remote="131578833600000000" />
<file name="1507528100maxresdefault.jpg" server="vacationhosting.com//public_html/" local="131574506400000000" remote="131574506400000000" />
<file name="1507528678food-715539_960_720.jpg" server="vacationhosting.com//public_html/" local="131574506400000000" remote="131574506400000000" />
<file name="1507977045exp3.jpg" server="vacationhosting.com//public_html/" local="131574506400000000" remote="131574506400000000" />
<file name="1508578049exp5.jpg" server="vacationhosting.com//public_html/" local="131574506400000000" remote="131574506400000000" />
<file name="1509017909slider4.jpg" server="vacationhosting.com//public_html/" local="131574506400000000" remote="131574506400000000" />
<file name="1510997532nature_two.jpg" server="vacationhosting.com//public_html/" local="131574506400000000" remote="131574506400000000" />
<file name="1510998396naturural_one.jpg" server="vacationhosting.com//public_html/" local="131574506400000000" remote="131574506400000000" />
<file name="1511003479food_one.jpg" server="vacationhosting.com//public_html/" local="131574506400000000" remote="131574506400000000" />
<file name="1511177730naturural_one.jpg" server="vacationhosting.com//public_html/" local="131574506400000000" remote="131574506400000000" />
<file name="1511181152art_fou.jpg" server="vacationhosting.com//public_html/" local="131574506400000000" remote="131574506400000000" />
<file name="1511430482majoc_one.jpg" server="vacationhosting.com//public_html/" local="131574506400000000" remote="131574506400000000" />
<file name="1511779069art_three.jpg" server="vacationhosting.com//public_html/" local="131574506400000000" remote="131574506400000000" />
<file name="1511782085artTwo.jpg" server="vacationhosting.com//public_html/" local="131574506400000000" remote="131574506400000000" />
<file name="15119534021507547430exp5.jpg" server="vacationhosting.com//public_html/" local="131574506400000000" remote="131574506400000000" />
<file name="1512803652nature_four.jpg" server="vacationhosting.com//public_html/" local="131574506400000000" remote="131574506400000000" />
<file name="1512816320artTwo.jpg" server="vacationhosting.com//public_html/" local="131574506400000000" remote="131574506400000000" />
<file name="1512826551majoc_one.jpg" server="vacationhosting.com//public_html/" local="131574506400000000" remote="131574506400000000" />
<file name="1512966751majoc_one.jpg" server="vacationhosting.com//public_html/" local="131577125400000000" remote="131577125400000000" />
<file name="1513085947nature_one.jpeg" server="vacationhosting.com//public_html/" local="131577125400000000" remote="131577125400000000" />
<file name="1513246059p7.jpg" server="vacationhosting.com//public_html/" local="131577963000000000" remote="131577963000000000" />
<file name="1513594391majoc_one.jpg" server="vacationhosting.com//public_html/" local="131581462200000000" remote="131581462200000000" />
<file name="1514923898Desert.jpg" server="vacationhosting.com//public_html/" local="131594064600000000" remote="131594064600000000" />
<file name="1515476022800 800--4.jpg" server="vacationhosting.com//public_html/" local="131599387800000000" remote="131599387800000000" />
<file name="1517633325nature_two.jpg" server="vacationhosting.com//public_html/" local="131620960800000000" remote="131620960800000000" />
<file name="1518011591nature_three.jpg" server="vacationhosting.com//public_html/" local="131624743800000000" remote="131624743800000000" />
<file name="151808327533223739.jpg" server="vacationhosting.com//public_html/" local="131625460200000000" remote="131625460200000000" />
<file name="1518651706ex3.jpg" server="vacationhosting.com//public_html/" local="131631144600000000" remote="131631144600000000" />
<file name="1518651859ex5.jpg" server="vacationhosting.com//public_html/" local="131631146400000000" remote="131631146400000000" />
<file name="1518719447two.jpg" server="vacationhosting.com//public_html/" local="131631822000000000" remote="131631822000000000" />
<file name="1520531384sight.jpg" server="vacationhosting.com//public_html/" local="131649941400000000" remote="131649941400000000" />
<file name="1520533182sa.jpg" server="vacationhosting.com//public_html/" local="131649959400000000" remote="131649959400000000" />
<file name="1520534293sa.jpg" server="vacationhosting.com//public_html/" local="131649970800000000" remote="131649970800000000" />
<file name="1520535554001.jpg" server="vacationhosting.com//public_html/" local="131649983400000000" remote="131649983400000000" />
<file name="1520536748sighte.jpg" server="vacationhosting.com//public_html/" local="131649995400000000" remote="131649995400000000" />
<file name="1520979260food.jpg" server="vacationhosting.com//public_html/" local="131654420400000000" remote="131654420400000000" />
<file name="2017-11-28.jpg" server="vacationhosting.com//public_html/" local="131590196400000000" remote="131590196400000000" />
<file name="4.jpg" server="vacationhosting.com//public_html/" local="131627126400000000" remote="131627126400000000" />
<file name="BingWallpaper-2017-05-22.jpg" server="vacationhosting.com//public_html/" local="131594633400000000" remote="131594633400000000" />
<file name="Chrysanthemum.jpg" server="vacationhosting.com//public_html/" local="131649467400000000" remote="131649467400000000" />
<file name="DSCN59891.jpg" server="vacationhosting.com//public_html/" local="131612907000000000" remote="131612907000000000" />
<file name="Desert.jpg" server="vacationhosting.com//public_html/" local="131649577200000000" remote="131649577200000000" />
<file name="GooglePlayStore.png" server="vacationhosting.com//public_html/" local="131593844400000000" remote="131593844400000000" />
<file name="How-to-be-successful.jpg" server="vacationhosting.com//public_html/" local="131643433800000000" remote="131643433800000000" />
<file name="Hydrangeas.jpg" server="vacationhosting.com//public_html/" local="131638487400000000" remote="131638487400000000" />
<file name="Jellyfish.jpg" server="vacationhosting.com//public_html/" local="131637394200000000" remote="131637394200000000" />
<file name="Lighthouse.jpg" server="vacationhosting.com//public_html/" local="131589253200000000" remote="131589253200000000" />
<file name="Thumbs.db" server="vacationhosting.com//public_html/" local="131594069400000000" remote="131594069400000000" />
<file name="Tulips.jpg" server="vacationhosting.com//public_html/" local="131591026800000000" remote="131591026800000000" />
<file name="aa.jpg" server="vacationhosting.com//public_html/" local="131578833600000000" remote="131578833600000000" />
<file name="adbg.jpg" server="vacationhosting.com//public_html/" local="131578833600000000" remote="131578833600000000" />
<file name="artTwo.jpg" server="vacationhosting.com//public_html/" local="131574506400000000" remote="131574506400000000" />
<file name="art_five.jpg" server="vacationhosting.com//public_html/" local="131574506400000000" remote="131574506400000000" />
<file name="art_fou.jpg" server="vacationhosting.com//public_html/" local="131574506400000000" remote="131574506400000000" />
<file name="art_four.jpg" server="vacationhosting.com//public_html/" local="131590090800000000" remote="131590090800000000" />
<file name="art_one.jpg" server="vacationhosting.com//public_html/" local="131590105200000000" remote="131590105200000000" />
<file name="art_three.jpg" server="vacationhosting.com//public_html/" local="131582278200000000" remote="131582278200000000" />
<file name="cricket.jpg" server="vacationhosting.com//public_html/" local="131574506400000000" remote="131574506400000000" />
<file name="dsfds.png" server="vacationhosting.com//public_html/" local="131578833600000000" remote="131578833600000000" />
<file name="dummyProductImage.jpg" server="vacationhosting.com//public_html/" local="131574506400000000" remote="131574506400000000" />
<file name="ef.jpg" server="vacationhosting.com//public_html/" local="131640519600000000" remote="131640519600000000" />
<file name="exp5.jpg" server="vacationhosting.com//public_html/" local="131574506400000000" remote="131574506400000000" />
<file name="food_five.jpg" server="vacationhosting.com//public_html/" local="131574506400000000" remote="131574506400000000" />
<file name="food_one.jpg" server="vacationhosting.com//public_html/" local="131574506400000000" remote="131574506400000000" />
<file name="majic_two.jpg" server="vacationhosting.com//public_html/" local="131616716400000000" remote="131616716400000000" />
<file name="majoc_one.jpg" server="vacationhosting.com//public_html/" local="131624742000000000" remote="131624742000000000" />
<file name="music.jpg" server="vacationhosting.com//public_html/" local="131635398600000000" remote="131635398600000000" />
<file name="nature_four.jpg" server="vacationhosting.com//public_html/" local="131624571000000000" remote="131624571000000000" />
<file name="nature_three.jpg" server="vacationhosting.com//public_html/" local="131624731200000000" remote="131624731200000000" />
<file name="p41.jpg" server="vacationhosting.com//public_html/" local="131590083000000000" remote="131590083000000000" />
<file name="party.jpg" server="vacationhosting.com//public_html/" local="131647602000000000" remote="131647602000000000" />
<file name="pexels-photo-588561.jpeg" server="vacationhosting.com//public_html/" local="131634462000000000" remote="131634462000000000" />
<file name="sal.jpg" server="vacationhosting.com//public_html/" local="131635389000000000" remote="131635389000000000" />
<file name="ski2.jpg" server="vacationhosting.com//public_html/" local="131644137000000000" remote="131644137000000000" />
<file name="test.jpg" server="vacationhosting.com//public_html/" local="131584294800000000" remote="131584294800000000" />
</dwsync>